llmfunc/__about__.py
llmfunc/__init__.py
llmfunc-0.0.1.dist-info/METADATA
llmfunc-0.0.1.dist-info/WHEEL
llmfunc-0.0.1.dist-info/licenses/LICENSE.txt
llmfunc-0.0.1.dist-info/RECORD
